loguru_loki_handler/__init__.py
loguru_loki_handler/loguru_loki_handler.py
loguru_loki_handler-0.1.1.dist-info/LICENSE
loguru_loki_handler-0.1.1.dist-info/METADATA
loguru_loki_handler-0.1.1.dist-info/WHEEL
loguru_loki_handler-0.1.1.dist-info/top_level.txt
loguru_loki_handler-0.1.1.dist-info/RECORD
