Metadata-Version: 2.1
Name: loguru-loki-handler
Version: 0.1.1
Summary: Handler created for Loguru that sends logs to Grafana Loki in JSON format
Home-page: https://github.com/xente/loguru-loki-handlers
Author: Xente
Keywords: loki,loguru
Classifier: Development Status :: 5 - Production/Stable
Classifier: Intended Audience :: Developers
Classifier: License :: OSI Approved :: MIT License
Classifier: Programming Language :: Python :: 3
Classifier: Programming Language :: Python :: 3.6
Classifier: Programming Language :: Python :: 3.7
Classifier: Programming Language :: Python :: 3.8
Classifier: Programming Language :: Python :: 3.9
License-File: LICENSE
